{
  "language_code": "eng",
  "language_probability": 1,
  "text": "I look magical",
  "words": [
    {
      "text": "I",
      "start": 0.059,
      "end": 0.179,
      "type": "word",
      "logprob": -0.0000034570634852570947
    },
    {
      "text": " ",
      "start": 0.179,
      "end": 0.199,
      "type": "spacing",
      "logprob": -0.000007033323527139146
    },
    {
      "text": "look",
      "start": 0.199,
      "end": 0.379,
      "type": "word",
      "logprob": -0.000007033323527139146
    },
    {
      "text": " ",
      "start": 0.379,
      "end": 0.419,
      "type": "spacing",
      "logprob": -0.0000040531076592742465
    },
    {
      "text": "magical",
      "start": 0.419,
      "end": 0.879,
      "type": "word",
      "logprob": -0.0000040531076592742465
    }
  ],
  "transcription_id": "ogtLiJP0Eh5XiN58YV4S",
  "audio_duration_secs": 1.2074375
}
